LICENSE
MANIFEST.in
README.md
requirements.txt
setup.py
nulb/__init__.py
nulb/main.py
nulb.egg-info/PKG-INFO
nulb.egg-info/SOURCES.txt
nulb.egg-info/dependency_links.txt
nulb.egg-info/entry_points.txt
nulb.egg-info/requires.txt
nulb.egg-info/top_level.txt